Metadata-Version: 2.4
Name: llama-index-vector-stores-tidbvector
Version: 0.4.1
Summary: llama-index vector-stores tidbvector integration
Author-email: Your Name <you@example.com>
License-Expression: MIT
License-File: LICENSE
Requires-Python: <4.0,>=3.9
Requires-Dist: llama-index-core<0.15,>=0.13.0
Requires-Dist: pymysql<2,>=1.1.0
Requires-Dist: sqlalchemy<3,>=1.4
Requires-Dist: tidb-vector[client]<1.0.0,>=0.0.3
